quanario
